{
  "id": "f01156da-fd43-470d-a35f-fdb4ed1bd090",
  "prevId": "00000000-0000-0000-0000-000000000000",
  "version": "7",
  "dialect": "postgresql",
  "tables": {
    "public.cell_tags": {
      "name": "cell_tags",
      "schema": "",
      "columns": {
        "id": {
          "name": "id",
          "type": "serial",
          "primaryKey": true,
          "notNull": true
        },
        "cell_name": {
          "name": "cell_name",
          "type": "varchar(100)",
          "primaryKey": false,
          "notNull": true
        },
        "optix_path": {
          "name": "optix_path",
          "type": "varchar(255)",
          "primaryKey": false,
          "notNull": true
        },
        "symbol_name": {
          "name": "symbol_name",
          "type": "varchar(255)",
          "primaryKey": false,
          "notNull": true
        },
        "data_type": {
          "name": "data_type",
          "type": "varchar(50)",
          "primaryKey": false,
          "notNull": true
        },
        "array_dimensions": {
          "name": "array_dimensions",
          "type": "varchar(50)",
          "primaryKey": false,
          "notNull": false
        },
        "node_id": {
          "name": "node_id",
          "type": "varchar(100)",
          "primaryKey": false,
          "notNull": false
        },
        "description": {
          "name": "description",
          "type": "text",
          "primaryKey": false,
          "notNull": false
        },
        "selectable": {
          "name": "selectable",
          "type": "boolean",
          "primaryKey": false,
          "notNull": true
        }
      },
      "indexes": {},
      "foreignKeys": {},
      "compositePrimaryKeys": {},
      "uniqueConstraints": {},
      "policies": {},
      "checkConstraints": {},
      "isRLSEnabled": false
    }
  },
  "enums": {},
  "schemas": {},
  "sequences": {},
  "roles": {},
  "policies": {},
  "views": {},
  "_meta": {
    "columns": {},
    "schemas": {},
    "tables": {}
  }
}